[
  {
    "id": 1,
    "TeamA": "Uruguay",
    "Score": "0:0",
    "TeamB": "Korea Republic",
    "MatchDate": "24.11.22"
  },
  {
    "id": 2,
    "TeamA": "Portugal",
    "Score": "3:2",
    "TeamB": "Ghana",
    "MatchDate": "24.11.22"
  },
  {
    "id": 3,
    "TeamA": "Korea Republic",
    "Score": "2:3",
    "TeamB": "Ghana",
    "MatchDate": "28.11.22"
  },
  {
    "id": 4,
    "TeamA": "Portugal",
    "Score": "2:0",
    "TeamB": "Uruguay",
    "MatchDate": "28.11.22"
  },
  {
    "id": 5,
    "TeamA": "Ghana",
    "Score": "0:2",
    "TeamB": "Uruguay",
    "MatchDate": "02.12.22"
  },
  {
    "id": 6,
    "TeamA": "Korea Republic",
    "Score": "2:1",
    "TeamB": "Portugal",
    "MatchDate": "02.12.22"
  }
]