[
  {
    "id": 1,
    "Flag": "https://images.sports.gracenote.com/images/lib/basic/geo/country/flag/large/2241.png",
    "Country": "Japan",
    "Played": 3,
    "Win": 2,
    "Draw": 0,
    "Lose": 1,
    "Points": 6,
    "GoalsFor": 4,
    "GoalsAgainst": 3,
    "GoalDifference": 1,
    "AdvanceToNextRound": "Y"
  },
  {
    "id": 2,
    "Flag": "https://images.sports.gracenote.com/images/lib/basic/geo/country/flag/large/2203.png",
    "Country": "Spain",
    "Played": 3,
    "Win": 1,
    "Draw": 1,
    "Lose": 1,
    "Points": 4,
    "GoalsFor": 9,
    "GoalsAgainst": 3,
    "GoalDifference": 6,
    "AdvanceToNextRound": "Y"
  },
  {
    "id": 3,
    "Flag": "https://images.sports.gracenote.com/images/lib/basic/geo/country/flag/large/2206.png",
    "Country": "Germany",
    "Played": 3,
    "Win": 1,
    "Draw": 1,
    "Lose": 1,
    "Points": 4,
    "GoalsFor": 6,
    "GoalsAgainst": 5,
    "GoalDifference": 1,
    "AdvanceToNextRound": "N"
  },
  {
    "id": 4,
    "Flag": "https://images.sports.gracenote.com/images/lib/basic/geo/country/flag/large/2771.png",
    "Country": "Costa Rica",
    "Played": 3,
    "Win": 1,
    "Draw": 0,
    "Lose": 2,
    "Points": 3,
    "GoalsFor": 3,
    "GoalsAgainst": 11,
    "GoalDifference": -8,
    "AdvanceToNextRound": "N"
  }
]